[
  {
    "id": "1774012752405",
    "name": "sean",
    "email": "seanortegapulga13@gmail.com",
    "passwordHash": "$2b$10$9wZ0aqR3aYtr7cP6aM6oGuS8nNHAt406tCLmOpIMrVBeYgfOexx6e",
    "bucketList": [
      {
        "destinationId": "paris-fr",
        "targetDate": "",
        "status": "Planned",
        "addedAt": "2026-03-20T13:19:19.737Z"
      },
      {
        "destinationId": "bali-id",
        "targetDate": "",
        "status": "Planned",
        "addedAt": "2026-03-20T13:19:23.757Z"
      },
      {
        "destinationId": "banff-ca",
        "targetDate": "",
        "status": "Planned",
        "addedAt": "2026-03-20T13:19:25.260Z"
      }
    ]
  },
  {
    "id": 1774013958191,
    "name": "API Test",
    "email": "apitest486457480@mail.com",
    "password": "$2b$10$xXPRFoQxWniPPr29FHM1pOBCuizruQpYnSZWb.Un05XBUdN8wTak2",
    "created_at": "2026-03-20T13:39:18.191Z"
  },
  {
    "id": 1774148957770,
    "name": "Test User",
    "email": "test@example.com",
    "password": "$2b$10$mUsa8H6E5pLWNaRNxdERf.y8Tv1jS/PG67DhQAL4ZlwVrqyHf0H6q",
    "created_at": "2026-03-22T03:09:17.770Z"
  }
]
